{"qese": 1, "nomre": 2, "i": 3, "qeydiya": 4, "ke": 5, "mesaj": 6, "gelir": 7, "tetbiq": 8, "islemir": 9, "ca": 10, "ba": 11, "bilmire": 12, "ko": 13, "bilersiz": 14, "gozel": 15, "xa": 16, "edire": 17, "problemi": 18, "hell": 19, "ed": 20, "hefte": 21, "2": 22, "defe": 23, "carx": 24, "gel": 25, "faiz": 26, "teref": 27, "se": 28, "ni": 29, "\ud83e\udd26": 30, "progra": 31, "acir": 32, "kar": 33, "kecir": 34, "isteyire": 35, "deyir": 36, "3d": 37, "olmali": 38, "kapital": 39, "bank": 40, "kecmir": 41, "elaaa": 42, "pragram": 43, "tesekur": 44, "tetbiqiniz": 45, "berbad": 46, "emeyi": 47, "kece": 48, "kese": 49, "tesekkur": 50, "al": 51, "ver": 52, "proqrami": 53, "goz": 54, "sup": 55, "keyfiyyetli": 56, "a": 57, "basqa": 58, "karti": 59, "qeydiyya": 60, "bilere": 61, "beyenire": 62, "\ud83d\udc4d": 63, "gu": 64, "tez": 65, "qa": 66, "v": 67, "yox": 68, "olmur": 69, "abune": 70, "cix": 71, "alinmir": 72, "olur": 73, "duzeld": 74, "prob": 75, "tek": 76, "taksi": 77, "telefo": 78, "meblegi": 79, "gostermir": 80, "etmeliye": 81, "qeseng": 82, "yaxsi": 83, "\ud83c\udffb": 84, "proqram": 85, "ara": 86, "yaxwi": 87, "superr": 88, "proqra": 89, "gir": 90, "don": 91, "qal": 92, "mese": 93, "ehse": 94, "sene": 95, "bakcell": 96, "zor": 97, "guncelle": 98, "uygu": 99, "cooox": 100, "allah": 101, "zeh": 102, "biri": 103, "xeta": 104, "yenile": 105, "hal": 106, "teleb": 107, "p": 108, "evvel": 109, "de": 110, "bol": 111, "ged": 112, "goster": 113, "size": 114, "sifarisi": 115, "kec": 116, "acilmir": 117, "raha": 118, "super": 119, "\ud83d\ude0e": 120, "bonu": 121, "yuksek": 122, "ol": 123, "deqiqe": 124, "dig": 125, "mob": 126, "operator": 127, "olsu": 128, "f": 129, "qed": 130, "etdik": 131, "kod": 132, "endiri": 133, "ode": 134, "isteye": 135, "gore": 136, "zamani": 137, "ustu": 138, "qeyd": 139, "bilmir": 140, "sehv": 141, "cixir": 142, "daha": 143, "artiq": 144, "gah": 145, "isleyir": 146, "bezi": 147, "lazim": 148, "hesab": 149, "qara": 150, "sal": 151, "yazilir": 152, "meni": 153, "gelse": 154, "we": 155, "bunu": 156, "razi": 157, "bur": 158, "limitsiz": 159, "interne": 160, "basa": 161, "yalniz": 162, "ge": 163, "sureti": 164, "qe": 165, "paketleri": 166, "sagolu": 167, "neye": 168, "deye": 169, "1": 170, "yaz": 171, "cok": 172, "guzel": 173, "ta": 174, "mebleg": 175, "olun": 176, "da": 177, "uzre": 178, "kocur": 179, "ac": 180, "qiymetleri": 181, "gire": 182, "sifre": 183, "isteyir": 184, "normal": 185, "\ud83e\udd17": 186, "istifa": 187, "meslehe": 188, "xid": 189, "pulsuz": 190, "ilk": 191, "be": 192, "acmir": 193, "sm": 194, "gelmir": 195, "yarayir": 196, "ozu": 197, "acilir": 198, "olmasa": 199, "faydali": 200, "suali": 201, "umico": 202, "oz": 203, "hem": 204, "kecire": 205, "bili": 206, "cavab": 207, "isledire": 208, "xosu": 209, "ugur": 210, "zeng": 211, "catdir": 212, "eyni": 213, "wol": 214, "sifar": 215, "qeb": 216, "etmir": 217, "biraz": 218, "10": 219, "mana": 220, "ev": 221, "100": 222, "50": 223, "qepik": 224, "qo": 225, "edv": 226, "yuklenir": 227, "he": 228, "\ud83d\udda4": 229, "ic": 230, "ela": 231, "serfeli": 232, "sevire": 233, "yuk": 234, "eseb": 235, "bawqa": 236, "ede": 237, "yukleye": 238, "co": 239, "ise": 240, "musteri": 241, "kimi": 242, "meslehetli": 243, "bugu": 244, "yeni": 245, "yasa": 246, "duz": 247, "haqqi": 248, "suru": 249, "mene": 250, "seher": 251, "bi": 252, "varsa": 253, "donur": 254, "yenilenmir": 255, "girmir": 256, "ekra": 257, "yene": 258, "meqabay": 259, "girir": 260, "superrrr": 261, "cek": 262, "unva": 263, "goture": 264, "birse": 265, "olsa": 266, "qr": 267, "geri": 268, "imka": 269, "hediye": 270, "veri": 271, "cixa": 272, "isdeyir": 273, "ona": 274, "\ud83d\ude4f": 275, "oldugu": 276, "hec": 277, "duzgu": 278, "olu": 279, "telefonum": 280, "praqrami": 281, "\ud83e\udd70": 282, "ok": 283, "beye": 284, "sehf": 285, "\ud83d\ude21": 286, "mukemmel": 287, "seyi": 288, "fa": 289, "verir": 290, "vax": 291, "kabine": 292, "nomresi": 293, "balansini": 294, "artir": 295, "olar": 296, "vesai": 297, "sa": 298, "istediyi": 299, "sata": 300, "\ud83d\udc4e": 301, "raziya": 302, "sati": 303, "tap": 304, "yara": 305, "\u2764\ufe0f": 306, "beyenil": 307, "asanlasdirir": 308, "\ud83d\ude09": 309, "say": 310, "pox": 311, "axi": 312, "siki": 313, "b": 314, "komunal": 315, "evvelki": 316, "pake": 317, "kontur": 318, "\u2764": 319, "yukle": 320, "vaxta": 321, "baba": 322, "gorure": 323, "elaaaaaa": 324, "seviyye": 325, "sagol": 326, "pa": 327, "hecne": 328, "vermir": 329, "tetbiqi": 330, "hamiya": 331, "tovsiyye": 332, "edirem": 333, "el": 334, "baha": 335, "qiymeti": 336, "asagi": 337, "serf": 338, "guncel": 339, "adami": 340, "edirsiz": 341, "herse": 342, "teze": 343, "berba": 344, "sifreni": 345, "yaza": 346, "ha": 347, "qos": 348, "te": 349, "odenisi": 350, "yani": 351, "tovsiye": 352, "cur": 353, "emeliyya": 354, "bilirse": 355, "nomreni": 356, "dax": 357, "mumku": 358, "gon": 359, "yazir": 360, "duzel": 361, "i\u0307slemir": 362, "i\u0307": 363, "ancaq": 364, "hesabi": 365, "app": 366, "idare": 367, "xah": 368, "yararli": 369, "coxu": 370, "praqram": 371, "komek": 372, "sef": 373, "bloka": 374, "du": 375, "gorse": 376, "biler": 377, "so": 378, "ali": 379, "bilir": 380, "soz": 381, "insa": 382, "umumi": 383, "za": 384, "muna": 385, "qiy": 386, "odenisleri": 387, "edre": 388, "bag": 389, "hansisa": 390, "sebebi": 391, "yazi": 392, "muveqqeti": 393, "vaxti": 394, "12": 395, "telefonu": 396, "lalafo": 397, "bil": 398, "isi": 399, "mb": 400, "gotur": 401, "nese": 402, "melu": 403, "lazi": 404, "praqra": 405, "iwlemir": 406, "qaldir": 407, "yeri": 408, "ehtiyac": 409, "firildaq": 410, "vere": 411, "bomba": 412, "5": 413, "ulduz": 414, "haqq": 415, "destek": 416, "apar": 417, "pullu": 418, "20": 419, "bezdir": 420, "konullu": 421, "unibank": 422, "program": 423, "do": 424, "lap": 425, "ka": 426, "kartini": 427, "sek": 428, "pulu": 429, "har": 430, "deyerdiz": 431, "komissiya": 432, "deyi": 433, "kredi": 434, "xidmetleri": 435, "30": 436, "prab": 437, "yaranir": 438, "alda": 439, "gelecek": 440, "leobank": 441, "c": 442, "6": 443, "200": 444, "deq": 445, "danisiq": 446, "aciq": 447, "\ud83e\udd19": 448, "onu": 449, "coxx": 450, "qaqa": 451, "online": 452, "kampaniya": 453, "tecili": 454, "aktiv": 455, "oyre": 456, "qane": 457, "mohtese": 458, "basi": 459, "sirke": 460, "yere": 461, "rek": 462, "etmeye": 463, "buna": 464, "kartina": 465, "zeif": 466, "twk": 467, "hazir": 468, "tedbiq": 469, "filial": 470, "tesekkurumu": 471, "bildirire": 472, "bax": 473, "h": 474, "m10": 475, "et": 476, "cixilir": 477, "karta": 478, "yuklenmir": 479, "qaytar": 480, "asa": 481, "sure": 482, "esa": 483, "sehife": 484, "temiz": 485, "yer": 486, "4": 487, "on": 488, "0": 489, "bal": 490, "sistem": 491, "layiq": 492, "iki": 493, "artig": 494, "halal": 495, "lerik": 496, "nomremi": 497, "9": 498, "reqemli": 499, "suruculeri": 500, "promo": 501, "yax": 502, "nfc": 503, "xo": 504, "birbank": 505, "zib": 506, "gune": 507, "redd": 508, "var": 509, "cixar": 510, "carxi": 511, "\ud83d\ude42": 512, "\ud83d\udc4c": 513, "mal": 514, "ister": 515, "tarif": 516, "paketi": 517, "olke": 518, "edirik": 519, "yal": 520, "dava": 521, "vura": 522, "hemise": 523, "re": 524, "bagli": 525, "olunur": 526, "elave": 527, "etsez": 528, "gond": 529, "beli": 530, "heleki": 531, "gorek": 532, "internetsiz": 533, "adina": 534, "cixmir": 535, "haq": 536, "gorese": 537, "digital": 538, "isleye": 539, "gor": 540, "yari": 541, "aleyku": 542, "beyen": 543, "cetin": 544, "fuzuli": 545, "filialina": 546, "catir": 547, "d": 548, "odenisler": 549, "sayti": 550, "etseniz": 551, "herkese": 552, "iste": 553, "sikaye": 554, "yazira": 555, "ter": 556, "tutulur": 557, "legv": 558, "tewekkur": 559, "good": 560, "superrr": 561, "3": 562, "verer": 563, "yukleyire": 564, "mudde": 565, "isle": 566, "seh": 567, "deqiq": 568, "\ud83d\udc4f": 569, "problem": 570, "xetasi": 571, "dusur": 572, "error": 573, "\ud83d\udc96": 574, "eliyire": 575, "olunmur": 576, "gosterir": 577, "olmaya": 578, "versiya": 579, "cata": 580, "ye": 581, "lazimsiz": 582, "yariyir": 583, "yollari": 584, "olmasi": 585, "leo": 586, "orta": 587, "imtina": 588, "nomrem": 589, "si": 590, "nomreye": 591, "medeni": 592, "1gb": 593, "sebeke": 594, "verire": 595, "xeyirli": 596, "i\u0307stifa": 597, "m": 598, "faizi": 599, "xeyir": 600, "azerbayca": 601, "\ud83d\udc99": 602, "hediyye": 603, "server": 604, "elaqe": 605, "dene": 606, "bilmirsiz": 607, "dusmur": 608, "islese": 609, "7": 610, "isdiyir": 611, "yarad": 612, "ce": 613, "nie": 614, "tapa": 615, "ceki": 616, "getir": 617, "tetbiqe": 618, "elaa": 619, "gunu": 620, "axir": 621, "bolmesi": 622, "cevir": 623, "elanlari": 624, "\u2665\ufe0f": 625, "iba": 626, "mobi": 627, "mohtesem": 628, "yuklemise": 629, "insallah": 630, "yanl": 631, "\ud83d\ude0a": 632, "azercell": 633, "tu": 634, "tovsuye": 635, "the": 636, "you": 637, "baksel": 638, "funksiya": 639, "memnu": 640, "sora": 641, "getmir": 642, "\ud83c\udde6\ud83c\uddff": 643, "bakcel": 644, "sax": 645, "dune": 646, "olmaz": 647, "uzer": 648, "tofsiye": 649, "icine": 650, "eli": 651, "bi\u0307r": 652, "elaaaa": 653, "funksiyasi": 654, "yol": 655, "balansi": 656, "\ud83e\udd14": 657, "bare": 658, "bar": 659, "izi": 660, "tehlukesiz": 661, "tetbiqine": 662, "qoya": 663, "qaza": 664, "elani": 665, "500": 666, "deve": 667, "oluna": 668, "tarix": 669, "esl": 670, "u": 671, "rabite": 672, "sil": 673, "vallah": 674, "gozell": 675, "serv": 676, "i\u0307yi": 677, "verse": 678, "coox": 679, "ucuz": 680, "suruculeriniz": 681, "xidmetiniz": 682, "narazi": 683, "agir": 684, "yenilen": 685, "g": 686, "deyese": 687, "kodunu": 688, "ska": 689, "pis": 690, "siste": 691, "mecbur": 692, "beze": 693, "balansa": 694, "vur": 695, "nezere": 696, "marke": 697, "xerite": 698, "av": 699, "\ud83c\udffc": 700, "sozu": 701, "azercel": 702, "olunsa": 703, "zakaz": 704, "girire": 705, "verilmir": 706, "of": 707, "baxira": 708, "kecmise": 709, "tutur": 710, "limiti": 711, "eia": 712, "abb": 713, "gorsenmir": 714, "lazimli": 715, "bilire": 716, "yukluyure": 717, "yaramir": 718, "ozune": 719, "i\u0307nterne": 720, "bolmesine": 721, "bang": 722, "is": 723, "ellerinize": 724, "beynelxalq": 725, "gondere": 726, "etibarli": 727, "odeniw": 728, "xaiw": 729, "yerine": 730, "1000": 731, "olura": 732, "atir": 733, "iw": 734, "mehs": 735, "filiali": 736, "guclu": 737, "yoxa": 738, "deyire": 739, "15": 740, "erz": 741, "\ud83d\ude0d": 742, "isdifa": 743, "saa": 744, "reklami": 745, "elverisli": 746, "bize": 747, "boltu": 748, "yolu": 749, "xeb": 750, "naraziya": 751, "geseng": 752, "uc": 753, "iyi": 754, "bonusu": 755, "uje": 756, "onsuz": 757, "emelli": 758, "hesaba": 759, "sayi": 760, "sizi": 761, "nedense": 762, "elemir": 763, "60": 764, "movcud": 765, "minnetdara": 766, "nede": 767, "xidmeti": 768, "hami": 769, "cehd": 770, "texniki": 771, "\ud83d\ude18": 772, "zerdab": 773, "sebeb": 774, "ad": 775, "sagolsu": 776, "limi": 777, "halbuki": 778, "bor": 779, "\ud83e\udd29": 780, "yazirki": 781, "blok": 782, "sexse": 783, "vasitesi": 784, "etdiyi": 785, "almisa": 786, "aid": 787, "edilir": 788, "aca": 789, "kartim": 790, "yig": 791, "komeyi": 792, "umumiyye": 793, "isdeyire": 794, "youtube": 795, "ele": 796, "video": 797, "kesbek": 798, "elaaaaa": 799, "gic": 800, "qeydiyyata": 801, "gese": 802, "unvana": 803, "banka": 804, "teq": 805, "oyu": 806, "teklif": 807, "etmise": 808, "suretli": 809, "coxxx": 810, "gunde": 811, "ederdiz": 812, "tedbir": 813, "kartimi": 814, "edirse": 815, "deyirki": 816, "supersiz": 817, "yo": 818, "otur": 819, "yigira": 820, "gozleyire": 821, "resmi": 822, "tedbiqi": 823, "casback": 824, "bilmez": 825, "sifir": 826, "melumatlari": 827, "ik": 828, "sev": 829, "qarsi": 830, "maa": 831, "zeyif": 832, "dos": 833, "verirsiz": 834, "manata": 835, "gb": 836, "interneti": 837, "xowu": 838, "programi": 839, "gormure": 840, "qewe": 841, "isleri": 842, "sirketi": 843, "esya": 844, "isde": 845, "yarada": 846, "tsk": 847, "aparir": 848, "kohne": 849, "nezare": 850, "istiyire": 851, "deyqe": 852, "konulu": 853, "dai": 854, "menfi": 855, "odeye": 856, "yaradana": 857, "camaati": 858, "bizi": 859, "no": 860, "8": 861, "yar": 862, "iwleyir": 863, "sec": 864, "nomresini": 865, "guya": 866, "eladi": 867, "vac": 868, "ek": 869, "supp": 870, "muracie": 871, "qosu": 872, "girirse": 873, "qayi": 874, "yuklemeye": 875, "\ud83e\udd23": 876, "azersel": 877, "axtar": 878, "\ud83e\udd0c": 879, "bonuslari": 880, "yazilirki": 881, "istifadesi": 882, "k": 883, "silire": 884, "konturu": 885, "sevinere": 886, "firla": 887, "qeweng": 888, "sur": 889, "supe": 890, "defeler": 891, "masini": 892, "kodu": 893, "unvani": 894, "tekr": 895, "leng": 896, "uzaq": 897, "seliqeli": 898, "etmire": 899, "sexsi": 900, "hormetli": 901, "ayri": 902, "nar": 903, "qoyu": 904, "pe": 905, "perfec": 906, "mille": 907, "vurura": 908, "operativ": 909, "gorunmur": 910, "nagd": 911, "pulumu": 912, "or": 913, "qalir": 914, "gecik": 915, "telefona": 916, "ideal": 917, "fikir": 918, "bildir": 919, "sistemi": 920, "isliyir": 921, "gorunur": 922, "yaxsiki": 923, "verilir": 924, "yazirsa": 925, "baki": 926, "gozle": 927, "tapaz": 928, "uste": 929, "istese": 930, "ee": 931, "bez": 932, "baxa": 933, "birbanka": 934, "bo": 935, "edek": 936, "tel": 937, "serefsiz": 938, "piraqram": 939, "gosderir": 940, "banki": 941, "silinir": 942, "kabineti": 943, "kocure": 944, "hetta": 945, "bunna": 946, "qiymete": 947, "borc": 948, "avtomatik": 949, "berpa": 950, "adam": 951, "alir": 952, "su": 953, "surucuye": 954, "belke": 955, "coooox": 956, "ata": 957, "get": 958, "etrafli": 959, "tetbiqini": 960, "debe": 961, "isdemir": 962, "dogru": 963, "sonu": 964, "yeq": 965, "zayi": 966, "istiyir": 967, "edesiz": 968, "196": 969, "fir": 970, "\ud83d\udc9c": 971, "maraqli": 972, "alira": 973, "proqramdir": 974, "pensiya": 975, "yaxud": 976, "bidene": 977, "bilmirik": 978, "ulduza": 979, "\ud83c\udffb\ud83c\udffb\ud83c\udffb": 980, "etse": 981, "pes": 982, "urek": 983, "hamisi": 984, "parol": 985, "kartlari": 986, "seni": 987, "oldugunu": 988, "like": 989, "ceke": 990, "reklam": 991, "pragra": 992, "olarki": 993, "gosdermir": 994, "i\u0307lk": 995, "goru": 996, "unutmusa": 997, "zibili": 998, "goog": 999, "besdir": 1000}